[
  {
    "id": 1,
    "title": "Hạt Giống Tâm Hồn 1 ",
    "author": "Unknown",
    "price": 120000,
    "image": "images/1.jpeg",
    "tags": ["HOT", "TOP DEAL"],
    "category": "tam-ly",
    "rating": 4,
    "sold": 3200,
    "description": "Bộ sách truyền cảm hứng về cuộc sống và tâm hồn.",
    "detail": "Bộ sách Hạt giống tâm hồn..."
  },
  {
    "id": 2,
    "title": "Đắc Nhân Tâm",
    "author": "Dale Carnegie",
    "price": 110000,
    "image": "images/2.jpg",
    "tags": ["HOT", "TOP DEAL"],
    "category": "ky-nang",
    "rating": 5,
    "sold": 4500
  },
  {
    "id": 3,
    "title": "Người Giàu Có Nhất Thành Babylon",
    "author": "George S. Clason",
    "price": 130000,
    "image": "images/3.jpg",
    "tags": ["HOT", "TOP DEAL"],
    "category": "kinh-te",
    "rating": 4,
    "sold": 2800,
    "description": "Bí quyết làm giàu...",
    "detail": "Cuốn sách nói tới người đàn ông..."
  },
  {
    "id": 4,
    "title": "Tuổi Trẻ Đáng Giá Bao Nhiêu",
    "author": "Robin Sharma",
    "price": 95000,
    "image": "images/4.jpg",
    "tags": ["HOT", "TOP DEAL"],
    "category": "phat-trien",
    "rating": 4,
    "sold": 3500,
    "description": "Sách dành cho tuổi trẻ...",
    "detail": "Cuốn sách này được viết bởi..."
  },
  {
    "id": 5,
    "title": "Bí Mật Tư Duy Triệu Phú",
    "author": "T. Harv Eker",
    "price": 140000,
    "image": "images/5.webp",
    "tags": ["HOT", "TOP DEAL"],
    "category": "kinh-te",
    "rating": 4,
    "sold": 2100,
    "description": "Hướng dẫn tư duy...",
    "detail": "Trong cuốn sách này..."
  },
  {
    "id": 6,
    "title": "Nghĩ Giàu Làm Giàu",
    "author": "Napoleon Hill",
    "price": 150000,
    "image": "images/6.webp",
    "tags": ["HOT", "TOP DEAL"],
    "category": "phat-trien",
    "rating": 5,
    "sold": 4000,
    "description": "Cẩm nang nổi tiếng..."
  },
  {
    "id": 7,
    "title": "Nhà Giả Kim",
    "author": "Paulo Coelho",
    "price": 90000,
    "image": "images/7.jpg",
    "tags": ["NEW", "TOP DEAL"],
    "category": "van-hoc",
    "rating": 4,
    "sold": 2500,
    "description": "Câu chuyện phiêu lưu..."
  },
  {
    "id": 8,
    "title": "Alchemist – Nhà Giả Kim",
    "author": "Paulo Coelho",
    "price": 100000,
    "image": "images/8.jpg",
    "tags": ["NEW", "TOP DEAL"],
    "category": "van-hoc",
    "rating": 4,
    "sold": 2700
  },
  {
    "id": 9,
    "title": "Đời Ngắn Đừng Ngủ Dài",
    "author": "Robin Sharma",
    "price": 85000,
    "image": "images/9.jpg",
    "tags": ["HOT", "TOP DEAL"],
    "category": "phat-trien",
    "rating": 4,
    "sold": 3200,
    "description": "Sách truyền cảm hứng..."
  },
  {
    "id": 10,
    "title": "Thế Giới Phẳng",
    "author": "Thomas L. Friedman",
    "price": 150000,
    "image": "images/10.jpg",
    "tags": ["HOT", "TOP DEAL"],
    "category": "kinh-te",
    "rating": 4,
    "sold": 2000
  },
  {
    "id": 11,
    "title": "Trọn Bộ 24 Tập Doraemon Dài",
    "author": "Fujiko F. Fujio",
    "price": 550000,
    "image": "images/11.webp",
    "tags": ["HOT", "TOP DEAL"],
    "category": "thieu-nhi",
    "rating": 4,
    "sold": 3100
  },
  {
    "id": 12,
    "title": "Con Đường Hạnh Phúc",
    "author": "Gelong Thubten",
    "price": 120000,
    "image": "images/12.webp",
    "tags": ["HOT", "TOP DEAL"],
    "category": "tam-ly",
    "rating": 4,
    "sold": 2800
  },
  {
    "id": 13,
    "title": "Cha giàu, cha nghèo",
    "author": "Robert Kiyosaki",
    "price": 140000,
    "image": "images/13.jpg",
    "tags": ["SALE", "CHÍNH HÃNG"],
    "category": "kinh-te",
    "rating": 5,
    "sold": 4200
  },
  {
    "id": 14,
    "title": "Những Người Khác",
    "author": "Martin Amis",
    "price": 120000,
    "image": "images/14.jpg",
    "tags": ["SALE", "CHÍNH HÃNG"],
    "category": "tam-ly",
    "rating": 4,
    "sold": 3500
  },
  {
    "id": 15,
    "title": "Trên Đường Băng",
    "author": "Tony Buổi Sáng",
    "price": 130000,
    "image": "image/15.jpg",
    "tags": ["SALE", "CHÍNH HÃNG"],
    "category": "phat-trien",
    "rating": 4,
    "sold": 2900
  },
  {
    "id": 16,
    "title": "Đọc Vị Bất Kỳ Ai",
    "author": "David J. Lieberman",
    "price": 150000,
    "image": "images/16.jpg",
    "tags": ["SALE", "CHÍNH HÃNG"],
    "category": "tam-ly",
    "rating": 4,
    "sold": 2700
  },
  {
    "id": 17,
    "title": "Combo - Cuốn sách tô màu đầu tiên của tớ 8T",
    "author": "Minh họa: Jenny Brown; Lời: Kirsteen Robsonown",
    "price": 90000,
    "image": "images/17.webp",
    "tags": ["SALE", "CHÍNH HÃNG"],
    "category": "thieu-nhi",
    "rating": 4,
    "sold": 3000
  },
  {
    "id": 18,
    "title": "Đi Tìm Lẽ Sống",
    "author": "Viktor E. Frankl",
    "price": 140000,
    "image": "images/18.jpg",
    "tags": ["SALE", "CHÍNH HÃNG"],
    "category": "tam-ly",
    "rating": 4,
    "sold": 3600
  },
  {
    "id": 19,
    "title": "Đừng Chạy Theo Số Đông",
    "author": "Kiên Trần",
    "price": 45000,
    "image": "images/19.jpg",
    "tags": ["FLASH", "TOP DEAL"],
    "category": "phat-trien",
    "rating": 5,
    "sold": 5000
  },
  {
    "id": 20,
    "title": "Sapiens",
    "author": "Yuval Noah Harari",
    "price": 150000,
    "image": "images/20.jpeg",
    "tags": ["FLASH", "TOP DEAL"],
    "category": "van-hoc",
    "rating": 4,
    "sold": 3100
  },
  {
    "id": 21,
    "title": "Tâm Lý Học Tội Phạm",
    "author": "Diệp Hồng Vũ",
    "price": 90000,
    "image": "images/21.webp",
    "tags": ["FLASH", "TOP DEAL"],
    "category": "tam-ly",
    "rating": 4,
    "sold": 1800
  },
  {
    "id": 22,
    "title": "Thiên Nga Đen",
    "author": "Nassim Nicholas Taleb",
    "price": 130000,
    "image": "images/22.webp",
    "tags": ["FLASH", "TOP DEAL"],
    "category": "kinh-te",
    "rating": 4,
    "sold": 2400
  }
]